spotify_assistant/User.py
spotify_assistant/__init__.py
spotify_assistant-1.0.7.dist-info/METADATA
spotify_assistant-1.0.7.dist-info/WHEEL
spotify_assistant-1.0.7.dist-info/LICENSE
spotify_assistant-1.0.7.dist-info/RECORD
