Metadata-Version: 2.1
Name: spotify-assistant
Version: 1.0.7
Summary: A package that makes spotify users' lives easier!
License: MIT
Author: Caroline Tang, Julie Song, Jenit Jain, Chester Wang
Requires-Python: >=3.9,<4.0
Classifier: License :: OSI Approved :: MIT License
Classifier: Programming Language :: Python :: 3
Classifier: Programming Language :: Python :: 3.9
Classifier: Programming Language :: Python :: 3.10
Classifier: Programming Language :: Python :: 3.11
Requires-Dist: pandas (>=1.5.3,<2.0.0)
Requires-Dist: spotipy (>=2.22.0,<3.0.0)
